Workbook

Sheet Stock by Plant & Material
A1: Company 2000 - Plant-wise / Material-wise Inventory
A2: Unrestricted + Quality + Blocked stock in base unit; snapshot as of 08 Sep 2026; source MARD (excludes deletion-flagged)
A4: Plant | B4: Material | C4: Description | D4: Base Unit | E4: Unrestricted | F4: Quality Insp. | G4: Blocked | H4: Total
A5: 2001 | B5: 000000000000000471 | C5: PAPER TUBE 57X280=100GRM D/B BLACK DOT | D5: NOS | E5: 0 | F5: 0 | G5: 0 | H5: =SUM(E5:G5) -> 0
A6: 2001 | B6: 000000000000000584 | C6: PAPER TUBE 57X290=120GRM D/B GREEN STAR | D6: NOS | E6: 0 | F6: 0 | G6: 0 | H6: =SUM(E6:G6) -> 0
A7: 2001 | B7: 000000000000001672 | C7: TEX | D7: KG | E7: 0 | F7: 0 | G7: 0 | H7: =SUM(E7:G7) -> 0
A8: 2001 | B8: 000010100033000017 | C8: GASKET FOR TURBO CHARGER 249323 | D8: NOS | E8: 0 | F8: 0 | G8: 0 | H8: =SUM(E8:G8) -> 0
A9: 2001 | B9: 000010100034000049 | C9: HINON MOTOR | D9: NOS | E9: 0 | F9: 0 | G9: 0 | H9: =SUM(E9:G9) -> 0
A10: 2001 | B10: 000010100034000050 | C10: TRAVERS BOX | D10: NOS | E10: 0 | F10: 0 | G10: 0 | H10: =SUM(E10:G10) -> 0
A11: 2001 | B11: 000010100043000005 | C11: BRECK LINER 2 1/2" | D11: MTR | E11: 0 | F11: 0 | G11: 0 | H11: =SUM(E11:G11) -> 0
A12: 2001 | B12: 000010200006000024 | C12: ALUM. ARM CABLE 240 SQMM X 3.5 CORE XLPE | D12: MTR | E12: 0 | F12: 0 | G12: 0 | H12: =SUM(E12:G12) -> 0
A13: 2001 | B13: 000010200006000060 | C13: 2 PAIR TELEPHONE CABLE | D13: MTR | E13: 0 | F13: 0 | G13: 0 | H13: =SUM(E13:G13) -> 0
A14: 2001 | B14: 000010200026000001 | C14: CABLE TIE SIZE 100 MM | D14: NOS | E14: 0 | F14: 0 | G14: 0 | H14: =SUM(E14:G14) -> 0
A15: 2001 | B15: 000010200026000002 | C15: CABLE TIE SIZE 150 MM | D15: NOS | E15: 0 | F15: 0 | G15: 0 | H15: =SUM(E15:G15) -> 0
A16: 2001 | B16: 000010200026000003 | C16: CABLE TIE SIZE 200 MM | D16: NOS | E16: 0 | F16: 0 | G16: 0 | H16: =SUM(E16:G16) -> 0
... A14822: 2005 | B14822: T110072BCSSNXXXXXX | C14822: TEX 110/72 BRT CATONIC LICHI N | D14822: KG | E14822: 0 | F14822: 0 | G14822: 0 | H14822: =SUM(E14822:G14822) -> 0

Sheet Plant summary
A1: Company 2000 - Plant Summary
A2: Aggregated from Sheet 'Stock by Plant & Material'; snapshot as of 08 Sep 2026
A4: Plant | B4: Plant Name | C4: Materials | D4: Unrestricted | E4: Quality Insp. | F4: Blocked
A5: 2001 | B5: Textile | C5: =COUNTIFS('Stock by Plant & Material'!$A$5:$A$14822,$A5) -> 6810 | D5: =SUMIFS('Stock by Plant & Material'!$E$5:$E$14822,'Stock by Plant & Material'!$A$5:$A$14822,$A5) -> 279698.7 | E5: =SUMIFS('Stock by Plant & Material'!$F$5:$F$14822,'Stock by Plant & Material'!$A$5:$A$14822,$A5) -> 0 | F5: =SUMIFS('Stock by Plant & Material'!$G$5:$G$14822,'Stock by Plant & Material'!$A$5:$A$14822,$A5) -> 0
A6: 2002 | B6: Dyeing | C6: =COUNTIFS('Stock by Plant & Material'!$A$5:$A$14822,$A6) -> 7968 | D6: =SUMIFS('Stock by Plant & Material'!$E$5:$E$14822,'Stock by Plant & Material'!$A$5:$A$14822,$A6) -> 2098218.9 | E6: =SUMIFS('Stock by Plant & Material'!$F$5:$F$14822,'Stock by Plant & Material'!$A$5:$A$14822,$A6) -> 0 | F6: =SUMIFS('Stock by Plant & Material'!$G$5:$G$14822,'Stock by Plant & Material'!$A$5:$A$14822,$A6) -> 0
A7: 2004 | B7: Dyed JW | C7: =COUNTIFS('Stock by Plant & Material'!$A$5:$A$14822,$A7) -> 31 | D7: =SUMIFS('Stock by Plant & Material'!$E$5:$E$14822,'Stock by Plant & Material'!$A$5:$A$14822,$A7) -> 3146.018 | E7: =SUMIFS('Stock by Plant & Material'!$F$5:$F$14822,'Stock by Plant & Material'!$A$5:$A$14822,$A7) -> 0 | F7: =SUMIFS('Stock by Plant & Material'!$G$5:$G$14822,'Stock by Plant & Material'!$A$5:$A$14822,$A7) -> 0
A8: 2005 | B8: Dyeing 2005 | C8: =COUNTIFS('Stock by Plant & Material'!$A$5:$A$14822,$A8) -> 9 | D8: =SUMIFS('Stock by Plant & Material'!$E$5:$E$14822,'Stock by Plant & Material'!$A$5:$A$14822,$A8) -> 861.84 | E8: =SUMIFS('Stock by Plant & Material'!$F$5:$F$14822,'Stock by Plant & Material'!$A$5:$A$14822,$A8) -> 0 | F8: =SUMIFS('Stock by Plant & Material'!$G$5:$G$14822,'Stock by Plant & Material'!$A$5:$A$14822,$A8) -> 0
A9: TOTAL | C9: =SUM(C5:C8) -> 14818 | D9: =SUM(D5:D8) -> 2381925.5 | E9: =SUM(E5:E8) -> 0 | F9: =SUM(F5:F8) -> 0
